{
  "youtube_shorts_korea": [
    {
      "rank": 1,
      "title": "NOT CUTE AND MORE",
      "artist": "EL. H"
    },
    {
      "rank": 2,
      "title": "blue",
      "artist": "yung kai"
    },
    {
      "rank": 3,
      "title": "Zoo",
      "artist": "Shakira"
    },
    {
      "rank": 4,
      "title": "So Cute",
      "artist": "김선호"
    },
    {
      "rank": 5,
      "title": "OVERDRIVE",
      "artist": "TWS"
    },
    {
      "rank": 6,
      "title": "SPAGHETTI (feat. Floppy)",
      "artist": "LE SSERAFIM"
    },
    {
      "rank": 7,
      "title": "街のドルフィン",
      "artist": "Kingo Hamada"
    },
    {
      "rank": 8,
      "title": "NO BATIDAO (Gostoso)",
      "artist": "GX.KAI & Daughter"
    },
    {
      "rank": 9,
      "title": "Sweet Potato",
      "artist": "Oneul"
    },
    {
      "rank": 10,
      "title": "Good Goodbye",
      "artist": "HWASA"
    }
  ]
}
